cobu/Plugin.py
cobu/Schema.py
cobu/__init__.py
cobu/cli.py
cobu/commands/Base.py
cobu/commands/__init__.py
cobu/commands/build.py
cobu/commands/dump.py
cobu/commands/list.py
cobu/config.py
cobu/helper.py
cobu-0.2.0.dist-info/entry_points.txt
cobu-0.2.0.dist-info/WHEEL
cobu-0.2.0.dist-info/METADATA
cobu-0.2.0.dist-info/RECORD
