Metadata-Version: 2.1
Name: cobu
Version: 0.2.0
Summary: 
Author: gilbus
Requires-Python: >=3.6,<4.0
Classifier: Programming Language :: Python :: 3
Classifier: Programming Language :: Python :: 3.6
Classifier: Programming Language :: Python :: 3.7
Requires-Dist: jinja2 (>=2.10,<3.0)
Requires-Dist: toml (>=0.10.0,<0.11.0)
